metamart_source_fivetran/__init__.py
metamart_source_fivetran/adapters.py
metamart_source_fivetran/base.py
metamart_source_fivetran/fivetran_api/__init__.py
metamart_source_fivetran/fivetran_api/api_models.py
metamart_source_fivetran/fivetran_api/main.py
metamart_source_fivetran/loader.py
metamart_source_fivetran/mock_tools.py
metamart_source_fivetran/models.py
metamart_source_fivetran/package_definitions.py
metamart_source_fivetran/py.typed
metamart_source_fivetran-0.1.2.dist-info/METADATA
metamart_source_fivetran-0.1.2.dist-info/WHEEL
metamart_source_fivetran-0.1.2.dist-info/RECORD
